peeper/__init__.py
peeper/__version__.py
peeper/help.py
raceup_peeper-0.0.1.dist-info/METADATA
raceup_peeper-0.0.1.dist-info/WHEEL
raceup_peeper-0.0.1.dist-info/top_level.txt
raceup_peeper-0.0.1.dist-info/RECORD
