Metadata-Version: 2.1
Name: raceup-peeper
Version: 0.0.1
Summary: A tool to dig deep into telemetry data
Home-page: https://raceup.github.io
Author: FSAE Team University of Padova - Race UP
Author-email: sirfoga@protonmail.com
License: UNKNOWN
Keywords: raceup fsae telemetry ml
Platform: UNKNOWN
